haidv_oo/__init__.py
haidv_oo-0.1.0.dist-info/WHEEL
haidv_oo-0.1.0.dist-info/METADATA
haidv_oo-0.1.0.dist-info/RECORD
