Metadata-Version: 2.1
Name: haidv-oo
Version: 0.1.0
Summary: 
Author: naviat
Author-email: haidv.ict@gmail.com
Requires-Python: >=3.7,<4.0
Classifier: Programming Language :: Python :: 3
Classifier: Programming Language :: Python :: 3.7
Classifier: Programming Language :: Python :: 3.8
Requires-Dist: pendulum (>=2.0.5,<3.0.0)
